tsallis_stat/__init__.py
tsallis_stat/q_algebra.py
tsallis_stat-0.5.0.dist-info/METADATA
tsallis_stat-0.5.0.dist-info/WHEEL
tsallis_stat-0.5.0.dist-info/RECORD
