Metadata-Version: 2.1
Name: tsallis-stat
Version: 0.5.0
Summary: 
Author: hzume
Author-email: yota040@gmail.com
Requires-Python: ==3.11.6
Classifier: Programming Language :: Python :: 3
Requires-Dist: numpy (>=1.26.3,<2.0.0)
Requires-Dist: pytest (>=7.4.4,<8.0.0)
